{
  "name": "tenants/jojEXkWF6WPdG0NO5WCv/resources/new/full_1778063578526_luxary spa bed.webp",
  "bucket": "demo-ultimate-booking.appspot.com",
  "metageneration": 1,
  "generation": 1778063578615,
  "contentType": "image/webp",
  "storageClass": "STANDARD",
  "contentDisposition": "inline",
  "downloadTokens": [
    "c81efa4e-73fb-4564-a695-6787530185b0"
  ],
  "etag": "6srZFIMphRppqZTtBdKKdXdM/pI",
  "customMetadata": {},
  "timeCreated": "2026-05-06T10:32:58.615Z",
  "updated": "2026-05-06T10:32:58.615Z",
  "size": 62546,
  "md5Hash": "QD3BwwTuE/f8OgU6lziAjg==",
  "crc32c": "851741016"
}